asb/__init__.py
asb-0.3.data/scripts/asb
asb-0.3.dist-info/METADATA
asb-0.3.dist-info/WHEEL
asb-0.3.dist-info/top_level.txt
asb-0.3.dist-info/RECORD
