Metadata-Version: 2.1
Name: asb
Version: 0.3
Summary: Python utility to capture android screen frames in real time and use with 3rd party libs like opencv.
Home-page: https://github.com/roj4s/android_screen_buffer
Author: Luis Rojas Aguilera
Author-email: rojas@icomp.ufam.edu.br
License: UNKNOWN
Platform: UNKNOWN
Classifier: Programming Language :: Python :: 3
Classifier: License :: OSI Approved :: MIT License
Classifier: Operating System :: OS Independent
Requires-Dist: certifi (==2019.9.11)
Requires-Dist: numpy (==1.17.4)
Requires-Dist: opencv-python (==4.1.2.30)
